s2spy/__init__.py
s2spy/preprocess.py
s2spy/rgdr/__init__.py
s2spy/rgdr/label_alignment.py
s2spy/rgdr/rgdr.py
s2spy/rgdr/utils.py
s2spy-0.4.1.dist-info/METADATA
s2spy-0.4.1.dist-info/WHEEL
s2spy-0.4.1.dist-info/licenses/LICENSE
s2spy-0.4.1.dist-info/RECORD
