Metadata-Version: 2.3
Name: s2spy
Version: 0.4.1
Summary: python package for s2s forecasts with ai
Project-URL: Bug Tracker, https://github.com/AI4S2S/ai4s2s/issues
Project-URL: Documentation, https://ai4s2s.readthedocs.io/
Project-URL: Homepage, https://github.com/AI4S2S/ai4s2s
Author: Yang Liu, Bart Schilperoort, Peter Kalverla, Jannes van Ingen, Sem Vijverberg, Claire Donnelly
Author-email: y.liu@esciencecenter.nl
Maintainer-email: Yang Liu <y.liu@esciencecenter.nl>, Bart Schilperoort <b.schilperoort@esciencecenter.nl>, Peter Kalverla <b.schilperoort@esciencecenter.nl>, Jannes van Ingen <jannes.van.ingen@s2s-ai.com>, Sem Vijverberg <sem.vijverberg@vu.nl>, Claire Donnelly <c.donnelly@esciencecenter.nl>
License-Expression: Apache-2.0
License-File: LICENSE
Keywords: AI,S2S
Classifier: Development Status :: 2 - Pre-Alpha
Classifier: Intended Audience :: Developers
Classifier: License :: OSI Approved :: Apache Software License
Classifier: Natural Language :: English
Classifier: Programming Language :: Python :: 3
Classifier: Programming Language :: Python :: 3.9
Classifier: Programming Language :: Python :: 3.10
Classifier: Programming Language :: Python :: 3.11
Requires-Python: <3.12,>3.8
Requires-Dist: dask
Requires-Dist: lilio
Requires-Dist: matplotlib
Requires-Dist: netcdf4
Requires-Dist: numpy
Requires-Dist: pandas
Requires-Dist: scikit-learn
Requires-Dist: scipy
Requires-Dist: xarray
Provides-Extra: dev
Requires-Dist: black; extra == 'dev'
Requires-Dist: bump2version; extra == 'dev'
Requires-Dist: hatch; extra == 'dev'
Requires-Dist: isort; extra == 'dev'
Requires-Dist: mypy; extra == 'dev'
Requires-Dist: pytest; extra == 'dev'
Requires-Dist: pytest-cov; extra == 'dev'
Requires-Dist: ruff; extra == 'dev'
Provides-Extra: docs
Requires-Dist: coverage[toml]; extra == 'docs'
Requires-Dist: myst-parser; extra == 'docs'
Requires-Dist: sphinx; extra == 'docs'
Requires-Dist: sphinx-autoapi; extra == 'docs'
Requires-Dist: sphinx-rtd-theme; extra == 'docs'
